babyplots/__init__.py
babyplots/babyplots.py
babyplots/js/CCapture.all.min.js
babyplots/js/babyplots.js
babyplots/js/babyplots.js.LICENSE.txt
babyplots/js/babyplots.js.map
babyplots/js/gif.worker.js
babyplots/templates/plot.html
babyplots/templates/save_plot.html
babyplots/utils/__init__.py
babyplots/utils/is_notebook.py
babyplots-1.7.0.dist-info/LICENSE
babyplots-1.7.0.dist-info/METADATA
babyplots-1.7.0.dist-info/WHEEL
babyplots-1.7.0.dist-info/top_level.txt
babyplots-1.7.0.dist-info/RECORD
