Metadata-Version: 2.1
Name: babyplots
Version: 1.7.0
Summary: Python package that allows the use of babyplots visualizations in jupyter notebooks
Home-page: https://github.com/derpylz/babyplots_py
Author: Nils Trost
Author-email: nils.trost@hotmail.de
License: UNKNOWN
Platform: UNKNOWN
Classifier: Programming Language :: Python :: 3
Classifier: License :: OSI Approved :: Apache Software License
Classifier: Operating System :: OS Independent
Requires-Python: >=3.6
License-File: LICENSE
